README.txt
setup.py
gremlinclient/__init__.py
gremlinclient/api.py
gremlinclient/connection.py
gremlinclient/graph.py
gremlinclient/log.py
gremlinclient/pool.py
gremlinclient/response.py
gremlinclient.egg-info/PKG-INFO
gremlinclient.egg-info/SOURCES.txt
gremlinclient.egg-info/dependency_links.txt
gremlinclient.egg-info/requires.txt
gremlinclient.egg-info/top_level.txt
gremlinclient/aiohttp_client/__init__.py
gremlinclient/aiohttp_client/client.py
gremlinclient/tornado_client/__init__.py
gremlinclient/tornado_client/client.py
tests/__init__.py
tests/test_aiohttp.py
tests/test_aiohttp_PEP492.py
tests/test_asyncio.py
tests/test_asyncio_PEP492.py
tests/test_requests.py
tests/test_ssl.py
tests/test_tornado.py
tests/test_tornado_PEP492.py
tests/test_trollius.py