Metadata-Version: 1.1
Name: gremlinclient
Version: 0.2.7
Summary: Python driver for TP3 Gremlin Server
Home-page: UNKNOWN
Author: davebshow
Author-email: davebshow@gmail.com
License: MIT
Platform: UNKNOWN
Classifier: Development Status :: 4 - Beta
Classifier: Intended Audience :: Developers
Classifier: License :: OSI Approved :: MIT License
Classifier: Operating System :: OS Independent
Classifier: Programming Language :: Python
